Metadata-Version: 2.1
Name: sbyUtils
Version: 0.2
Summary: Some basic utils for day to day python programming
Author: Shai Ben Yosef
